odoo/addons/purchase_order_report_hide_tax/README.rst
odoo/addons/purchase_order_report_hide_tax/__init__.py
odoo/addons/purchase_order_report_hide_tax/__manifest__.py
odoo/addons/purchase_order_report_hide_tax/i18n/it.po
odoo/addons/purchase_order_report_hide_tax/i18n/purchase_order_report_hide_tax.pot
odoo/addons/purchase_order_report_hide_tax/models/__init__.py
odoo/addons/purchase_order_report_hide_tax/models/account_tax_group.py
odoo/addons/purchase_order_report_hide_tax/models/purchase_order.py
odoo/addons/purchase_order_report_hide_tax/readme/CONFIGURE.md
odoo/addons/purchase_order_report_hide_tax/readme/CONTEXT.md
odoo/addons/purchase_order_report_hide_tax/readme/CONTRIBUTORS.md
odoo/addons/purchase_order_report_hide_tax/readme/DESCRIPTION.md
odoo/addons/purchase_order_report_hide_tax/readme/USAGE.md
odoo/addons/purchase_order_report_hide_tax/reports/purchase_order_report_template.xml
odoo/addons/purchase_order_report_hide_tax/static/description/icon.png
odoo/addons/purchase_order_report_hide_tax/static/description/index.html
odoo/addons/purchase_order_report_hide_tax/tests/__init__.py
odoo/addons/purchase_order_report_hide_tax/tests/test_purchase_order_report_hide_tax.py
odoo/addons/purchase_order_report_hide_tax/views/account_tax_group_views.xml
odoo_addon_purchase_order_report_hide_tax-18.0.1.0.1.dist-info/METADATA
odoo_addon_purchase_order_report_hide_tax-18.0.1.0.1.dist-info/WHEEL
odoo_addon_purchase_order_report_hide_tax-18.0.1.0.1.dist-info/top_level.txt
odoo_addon_purchase_order_report_hide_tax-18.0.1.0.1.dist-info/RECORD
